README.md
setup.cfg
setup.py
sentry_ldap_auth/__init__.py
sentry_ldap_auth/backend.py
sentry_ldap_auth.egg-info/PKG-INFO
sentry_ldap_auth.egg-info/SOURCES.txt
sentry_ldap_auth.egg-info/dependency_links.txt
sentry_ldap_auth.egg-info/not-zip-safe
sentry_ldap_auth.egg-info/requires.txt
sentry_ldap_auth.egg-info/top_level.txt