Metadata-Version: 2.1
Name: sentry-ldap-auth
Version: 2.8.1
Summary: A Sentry extension to add an LDAP server as an authentication source.
Home-page: http://github.com/banno/getsentry-ldap-auth
Author: Chad Killingsworth <chad.killingsworth@banno.com>, Barron Hagerman <barron.hagerman@banno.com>
Author-email: chad.killingsworth@banno.com
License: Apache-2.0
Download-URL: https://github.com/banno/getsentry-ldap-auth/tarball/2.8.1
Platform: UNKNOWN
Classifier: Framework :: Django
Classifier: Intended Audience :: Developers
Classifier: Intended Audience :: System Administrators
Classifier: Operating System :: OS Independent
Classifier: Topic :: Software Development
